[
  {
    "prod_title": "월간 플로라(Flora)(2026년 2월호)",
    "portrait_img_box src": "https://contents.kyobobook.co.kr/sih/fit-in/458x0/pdt/3904000586441.jpg",
    "prod_link href": "https://product.kyobobook.co.kr/detail/S000219157501"
  },
  {
    "prod_title": "월간 플로라(Flora)(2026년 1월호)",
    "portrait_img_box src": "https://contents.kyobobook.co.kr/sih/fit-in/458x0/pdt/3904000580166.jpg",
    "prod_link href": "https://product.kyobobook.co.kr/detail/S000218936265"
  },
  {
    "prod_title": "월간 플로라(Flora)(2025년 12월호)",
    "portrait_img_box src": "https://contents.kyobobook.co.kr/sih/fit-in/458x0/pdt/3904000573038.jpg",
    "prod_link href": "https://product.kyobobook.co.kr/detail/S000218704290"
  },
  {
    "prod_title": "월간 플로라(Flora)(2025년 11월호)",
    "portrait_img_box src": "",
    "prod_link href": "https://ebook-product.kyobobook.co.kr/dig/epd/ebook/E000012136094"
  },
  {
    "prod_title": "월간 플로라(Flora)(2025년 11월호)",
    "portrait_img_box src": "https://contents.kyobobook.co.kr/sih/fit-in/458x0/pdt/3904000566535.jpg",
    "prod_link href": "https://product.kyobobook.co.kr/detail/S000218315399"
  },
  {
    "prod_title": "월간 플로라(Flora)(2025년 10월호)",
    "portrait_img_box src": "",
    "prod_link href": "https://ebook-product.kyobobook.co.kr/dig/epd/ebook/E000012048692"
  },
  {
    "prod_title": "월간 플로라(Flora)(2025년 10월호)",
    "portrait_img_box src": "https://contents.kyobobook.co.kr/sih/fit-in/458x0/pdt/3904000559537.jpg",
    "prod_link href": "https://product.kyobobook.co.kr/detail/S000218053700"
  },
  {
    "prod_title": "월간 플로라(Flora)(2025년 9월호)",
    "portrait_img_box src": "https://contents.kyobobook.co.kr/sih/fit-in/458x0/pdt/3904000553856.jpg",
    "prod_link href": "https://product.kyobobook.co.kr/detail/S000217444463"
  },
  {
    "prod_title": "월간 플로라(Flora)(2025년 9월호)",
    "portrait_img_box src": "",
    "prod_link href": "https://ebook-product.kyobobook.co.kr/dig/epd/ebook/E000011889347"
  },
  {
    "prod_title": "월간 플로라(Flora)(2025년 8월호)",
    "portrait_img_box src": "",
    "prod_link href": "https://ebook-product.kyobobook.co.kr/dig/epd/ebook/E000011731881"
  },
  {
    "prod_title": "월간 플로라(Flora)(2025년 8월호)",
    "portrait_img_box src": "https://contents.kyobobook.co.kr/sih/fit-in/458x0/pdt/3904000547244.jpg",
    "prod_link href": "https://product.kyobobook.co.kr/detail/S000217192569"
  },
  {
    "prod_title": "월간 플로라(Flora)(2025년 7월호)",
    "portrait_img_box src": "",
    "prod_link href": "https://ebook-product.kyobobook.co.kr/dig/epd/ebook/E000011629809"
  },
  {
    "prod_title": "월간 플로라(Flora)(2025년 7월호)",
    "portrait_img_box src": "https://contents.kyobobook.co.kr/sih/fit-in/458x0/pdt/3904000541273.jpg",
    "prod_link href": "https://product.kyobobook.co.kr/detail/S000216951107"
  },
  {
    "prod_title": "월간 플로라(Flora)(2025년 6월호)",
    "portrait_img_box src": "",
    "prod_link href": "https://ebook-product.kyobobook.co.kr/dig/epd/ebook/E000011521566"
  },
  {
    "prod_title": "월간 플로라(Flora)(2025년 6월호)",
    "portrait_img_box src": "https://contents.kyobobook.co.kr/sih/fit-in/458x0/pdt/3904000534961.jpg",
    "prod_link href": "https://product.kyobobook.co.kr/detail/S000216702974"
  },
  {
    "prod_title": "월간 플로라(Flora)(2025년 5월호)",
    "portrait_img_box src": "",
    "prod_link href": "https://ebook-product.kyobobook.co.kr/dig/epd/ebook/E000011521434"
  },
  {
    "prod_title": "월간 플로라(Flora)(2025년 5월호)",
    "portrait_img_box src": "https://contents.kyobobook.co.kr/sih/fit-in/458x0/pdt/3904000528328.jpg",
    "prod_link href": "https://product.kyobobook.co.kr/detail/S000216406228"
  },
  {
    "prod_title": "월간 플로라(Flora)(2025년 4월호)",
    "portrait_img_box src": "",
    "prod_link href": "https://ebook-product.kyobobook.co.kr/dig/epd/ebook/E000011290036"
  },
  {
    "prod_title": "월간 플로라(Flora)(2025년 4월호)",
    "portrait_img_box src": "https://contents.kyobobook.co.kr/sih/fit-in/458x0/pdt/3904000521800.jpg",
    "prod_link href": "https://product.kyobobook.co.kr/detail/S000216180058"
  },
  {
    "prod_title": "월간 플로라(Flora)(2025년 3월호)",
    "portrait_img_box src": "",
    "prod_link href": "https://ebook-product.kyobobook.co.kr/dig/epd/ebook/E000011132305"
  },
  {
    "prod_title": "월간 플로라(Flora)(2025년 3월호)",
    "portrait_img_box src": "https://contents.kyobobook.co.kr/sih/fit-in/458x0/pdt/3904000515281.jpg",
    "prod_link href": "https://product.kyobobook.co.kr/detail/S000215934167"
  },
  {
    "prod_title": "월간 플로라(Flora)(2025년 2월호)",
    "portrait_img_box src": "",
    "prod_link href": "https://ebook-product.kyobobook.co.kr/dig/epd/ebook/E000011019381"
  },
  {
    "prod_title": "월간 플로라(Flora)(2025년 2월호)",
    "portrait_img_box src": "https://contents.kyobobook.co.kr/sih/fit-in/458x0/pdt/3904000508009.jpg",
    "prod_link href": "https://product.kyobobook.co.kr/detail/S000215648247"
  },
  {
    "prod_title": "월간 플로라(Flora)(2025년 1월호)",
    "portrait_img_box src": "https://contents.kyobobook.co.kr/sih/fit-in/458x0/pdt/3904000503103.jpg",
    "prod_link href": "https://product.kyobobook.co.kr/detail/S000215097734"
  },
  {
    "prod_title": "월간 플로라(Flora)(2025년 1월호)",
    "portrait_img_box src": "",
    "prod_link href": "https://ebook-product.kyobobook.co.kr/dig/epd/ebook/E000010819908"
  },
  {
    "prod_title": "월간 플로라(Flora)(2024년 12월호)",
    "portrait_img_box src": "",
    "prod_link href": "https://ebook-product.kyobobook.co.kr/dig/epd/ebook/E000010401170"
  },
  {
    "prod_title": "월간 플로라(Flora)(2024년 12월호)",
    "portrait_img_box src": "https://contents.kyobobook.co.kr/sih/fit-in/458x0/pdt/3904000496122.jpg",
    "prod_link href": "https://product.kyobobook.co.kr/detail/S000214883307"
  },
  {
    "prod_title": "월간 플로라(Flora)(2024년 11월호)",
    "portrait_img_box src": "",
    "prod_link href": "https://ebook-product.kyobobook.co.kr/dig/epd/ebook/E000009495335"
  },
  {
    "prod_title": "월간 플로라(Flora)(2024년 11월호)",
    "portrait_img_box src": "https://contents.kyobobook.co.kr/sih/fit-in/458x0/pdt/3904000490045.jpg",
    "prod_link href": "https://product.kyobobook.co.kr/detail/S000214650698"
  },
  {
    "prod_title": "월간 플로라(Flora)(2024년 10월호)",
    "portrait_img_box src": "https://contents.kyobobook.co.kr/sih/fit-in/458x0/pdt/3904000483511.jpg",
    "prod_link href": "https://product.kyobobook.co.kr/detail/S000214451651"
  },
  {
    "prod_title": "월간 플로라(Flora)(2024년 10월호)",
    "portrait_img_box src": "",
    "prod_link href": "https://ebook-product.kyobobook.co.kr/dig/epd/ebook/E000009495442"
  },
  {
    "prod_title": "월간 플로라(Flora)(2024년 9월호)",
    "portrait_img_box src": "",
    "prod_link href": "https://ebook-product.kyobobook.co.kr/dig/epd/ebook/E000008779572"
  },
  {
    "prod_title": "월간 플로라(Flora)(2024년 9월호)",
    "portrait_img_box src": "https://contents.kyobobook.co.kr/sih/fit-in/458x0/pdt/3904000476575.jpg",
    "prod_link href": "https://product.kyobobook.co.kr/detail/S000214158441"
  },
  {
    "prod_title": "월간 플로라(Flora)(2024년 8월호)",
    "portrait_img_box src": "",
    "prod_link href": "https://ebook-product.kyobobook.co.kr/dig/epd/ebook/E000008536541"
  },
  {
    "prod_title": "월간 플로라(Flora)(2024년 8월호)",
    "portrait_img_box src": "https://contents.kyobobook.co.kr/sih/fit-in/458x0/pdt/3904000470559.jpg",
    "prod_link href": "https://product.kyobobook.co.kr/detail/S000213921689"
  },
  {
    "prod_title": "월간 플로라(Flora)(2024년 7월호)",
    "portrait_img_box src": "https://contents.kyobobook.co.kr/sih/fit-in/458x0/pdt/3904000465005.jpg",
    "prod_link href": "https://product.kyobobook.co.kr/detail/S000213676021"
  },
  {
    "prod_title": "월간 FLORA 2024년 7월호",
    "portrait_img_box src": "",
    "prod_link href": "https://ebook-product.kyobobook.co.kr/dig/epd/ebook/E000008021699"
  },
  {
    "prod_title": "월간 플로라(Flora)(2024년 6월호)",
    "portrait_img_box src": "https://contents.kyobobook.co.kr/sih/fit-in/458x0/pdt/3904000457765.jpg",
    "prod_link href": "https://product.kyobobook.co.kr/detail/S000213425216"
  },
  {
    "prod_title": "월간 플로라(Flora)(2024년 5월호)",
    "portrait_img_box src": "https://contents.kyobobook.co.kr/sih/fit-in/458x0/pdt/3904000452463.jpg",
    "prod_link href": "https://product.kyobobook.co.kr/detail/S000213134285"
  },
  {
    "prod_title": "월간 플로라(Flora)(2024년 4월호)",
    "portrait_img_box src": "https://contents.kyobobook.co.kr/sih/fit-in/458x0/pdt/3904000445892.jpg",
    "prod_link href": "https://product.kyobobook.co.kr/detail/S000212807433"
  },
  {
    "prod_title": "월간 FLORA 2024년 3월호",
    "portrait_img_box src": "",
    "prod_link href": "https://ebook-product.kyobobook.co.kr/dig/epd/ebook/E000006851538"
  },
  {
    "prod_title": "월간 플로라(Flora)(2024년 3월호)",
    "portrait_img_box src": "https://contents.kyobobook.co.kr/sih/fit-in/458x0/pdt/3904000439785.jpg",
    "prod_link href": "https://product.kyobobook.co.kr/detail/S000212604598"
  },
  {
    "prod_title": "월간 FLORA 2024년 2월호",
    "portrait_img_box src": "",
    "prod_link href": "https://ebook-product.kyobobook.co.kr/dig/epd/ebook/E000006851623"
  },
  {
    "prod_title": "월간 FLORA 2024년 2월호",
    "portrait_img_box src": "",
    "prod_link href": "https://ebook-product.kyobobook.co.kr/dig/epd/ebook/E000006851434"
  },
  {
    "prod_title": "월간 플로라(Flora)(2024년 2월호)",
    "portrait_img_box src": "https://contents.kyobobook.co.kr/sih/fit-in/458x0/pdt/3904000433837.jpg",
    "prod_link href": "https://product.kyobobook.co.kr/detail/S000212176719"
  },
  {
    "prod_title": "월간 플로라(Flora)(2024년 1월호)",
    "portrait_img_box src": "https://contents.kyobobook.co.kr/sih/fit-in/458x0/pdt/3904000428369.jpg",
    "prod_link href": "https://product.kyobobook.co.kr/detail/S000211796521"
  },
  {
    "prod_title": "월간 플로라(Flora)(2023년 12월호)",
    "portrait_img_box src": "https://contents.kyobobook.co.kr/sih/fit-in/458x0/pdt/3904000421858.jpg",
    "prod_link href": "https://product.kyobobook.co.kr/detail/S000211545967"
  },
  {
    "prod_title": "월간 플로라(Flora)(2023년 11월호)",
    "portrait_img_box src": "https://contents.kyobobook.co.kr/sih/fit-in/458x0/pdt/3904000415727.jpg",
    "prod_link href": "https://product.kyobobook.co.kr/detail/S000210833232"
  },
  {
    "prod_title": "월간 FLORA 2023년 11월호",
    "portrait_img_box src": "",
    "prod_link href": "https://ebook-product.kyobobook.co.kr/dig/epd/ebook/E000005451133"
  },
  {
    "prod_title": "월간 플로라(Flora)(2023년 10월호)",
    "portrait_img_box src": "https://contents.kyobobook.co.kr/sih/fit-in/458x0/pdt/3904000410616.jpg",
    "prod_link href": "https://product.kyobobook.co.kr/detail/S000209650973"
  },
  {
    "prod_title": "월간 플로라(Flora)(2023년 9월호)",
    "portrait_img_box src": "https://contents.kyobobook.co.kr/sih/fit-in/458x0/pdt/3904000402864.jpg",
    "prod_link href": "https://product.kyobobook.co.kr/detail/S000208721315"
  },
  {
    "prod_title": "월간 FLORA 2023년 9월호",
    "portrait_img_box src": "",
    "prod_link href": "https://ebook-product.kyobobook.co.kr/dig/epd/ebook/E000005382713"
  },
  {
    "prod_title": "임신과 출산에 어울리는 꽃 디자인",
    "portrait_img_box src": "",
    "prod_link href": "https://ebook-product.kyobobook.co.kr/dig/epd/ebook/E000005341656"
  },
  {
    "prod_title": "월간 플로라(Flora)(2023년 8월호)",
    "portrait_img_box src": "https://contents.kyobobook.co.kr/sih/fit-in/458x0/pdt/3904000397146.jpg",
    "prod_link href": "https://product.kyobobook.co.kr/detail/S000208257475"
  },
  {
    "prod_title": "월간 FLORA 2023년 8월호",
    "portrait_img_box src": "",
    "prod_link href": "https://ebook-product.kyobobook.co.kr/dig/epd/ebook/E000005329493"
  },
  {
    "prod_title": "한 권으로 보는 프리저브드 플라워",
    "portrait_img_box src": "",
    "prod_link href": "https://ebook-product.kyobobook.co.kr/dig/epd/ebook/E000005288222"
  },
  {
    "prod_title": "한 권으로 보는 전례꽃꽂이",
    "portrait_img_box src": "",
    "prod_link href": "https://ebook-product.kyobobook.co.kr/dig/epd/ebook/E000005288220"
  },
  {
    "prod_title": "월간 플로라(Flora)(2023년 7월호)",
    "portrait_img_box src": "https://contents.kyobobook.co.kr/sih/fit-in/458x0/pdt/3904000390840.jpg",
    "prod_link href": "https://product.kyobobook.co.kr/detail/S000202827421"
  },
  {
    "prod_title": "월간 FLORA 2023년 7월호",
    "portrait_img_box src": "",
    "prod_link href": "https://ebook-product.kyobobook.co.kr/dig/epd/ebook/E000005278187"
  },
  {
    "prod_title": "워터가든 모아보기",
    "portrait_img_box src": "",
    "prod_link href": "https://ebook-product.kyobobook.co.kr/dig/epd/ebook/E000005262782"
  },
  {
    "prod_title": "월간 플로라(Flora)(2023년 6월호)",
    "portrait_img_box src": "https://contents.kyobobook.co.kr/sih/fit-in/458x0/pdt/3904000384313.jpg",
    "prod_link href": "https://product.kyobobook.co.kr/detail/S000202478958"
  },
  {
    "prod_title": "이달의 꽃",
    "portrait_img_box src": "",
    "prod_link href": "https://ebook-product.kyobobook.co.kr/dig/epd/ebook/E000005239973"
  },
  {
    "prod_title": "월간 FLORA 2023년 6월호",
    "portrait_img_box src": "",
    "prod_link href": "https://ebook-product.kyobobook.co.kr/dig/epd/ebook/E000005231192"
  },
  {
    "prod_title": "월간 FLORA 2023년 5월호",
    "portrait_img_box src": "",
    "prod_link href": "https://ebook-product.kyobobook.co.kr/dig/epd/ebook/E000005205244"
  },
  {
    "prod_title": "월간 플로라(Flora)(2023년 5월호)",
    "portrait_img_box src": "https://contents.kyobobook.co.kr/sih/fit-in/458x0/pdt/3904000378466.jpg",
    "prod_link href": "https://product.kyobobook.co.kr/detail/S000201794311"
  },
  {
    "prod_title": "월간 FLORA 2023년 4월호",
    "portrait_img_box src": "",
    "prod_link href": "https://ebook-product.kyobobook.co.kr/dig/epd/ebook/E000005170701"
  },
  {
    "prod_title": "월간 플로라(Flora)(2023년 4월호)",
    "portrait_img_box src": "https://contents.kyobobook.co.kr/sih/fit-in/458x0/pdt/3904000371399.jpg",
    "prod_link href": "https://product.kyobobook.co.kr/detail/S000201360836"
  },
  {
    "prod_title": "월간 FLORA 2023년 3월호",
    "portrait_img_box src": "",
    "prod_link href": "https://ebook-product.kyobobook.co.kr/dig/epd/ebook/E000005134474"
  },
  {
    "prod_title": "월간 플로라(Flora)(2023년 3월호)",
    "portrait_img_box src": "https://contents.kyobobook.co.kr/sih/fit-in/458x0/pdt/3904000365701.jpg",
    "prod_link href": "https://product.kyobobook.co.kr/detail/S000201160902"
  },
  {
    "prod_title": "월간 플로라(Flora)(2023년 2월호)",
    "portrait_img_box src": "https://contents.kyobobook.co.kr/sih/fit-in/458x0/pdt/3904000358734.jpg",
    "prod_link href": "https://product.kyobobook.co.kr/detail/S000200787686"
  },
  {
    "prod_title": "월간 FLORA 2023년 2월호",
    "portrait_img_box src": "",
    "prod_link href": "https://ebook-product.kyobobook.co.kr/dig/epd/ebook/E000005105675"
  },
  {
    "prod_title": "월간 FLORA 2023년 1월호",
    "portrait_img_box src": "",
    "prod_link href": "https://ebook-product.kyobobook.co.kr/dig/epd/ebook/E000005079429"
  },
  {
    "prod_title": "월간 플로라(Flora)(2023년 1월호)",
    "portrait_img_box src": "https://contents.kyobobook.co.kr/sih/fit-in/458x0/pdt/3904000352640.jpg",
    "prod_link href": "https://product.kyobobook.co.kr/detail/S000200554180"
  },
  {
    "prod_title": "월간 FLORA 2022년 12월호",
    "portrait_img_box src": "",
    "prod_link href": "https://ebook-product.kyobobook.co.kr/dig/epd/ebook/E000005050518"
  },
  {
    "prod_title": "월간 플로라(Flora)(2022년 12월호)",
    "portrait_img_box src": "https://contents.kyobobook.co.kr/sih/fit-in/458x0/pdt/3904000345390.jpg",
    "prod_link href": "https://product.kyobobook.co.kr/detail/S000200330305"
  },
  {
    "prod_title": "월간 FLORA 2022년 11월호",
    "portrait_img_box src": "",
    "prod_link href": "https://ebook-product.kyobobook.co.kr/dig/epd/ebook/E000005018110"
  },
  {
    "prod_title": "월간 플로라(Flora)(2022년 11월호)",
    "portrait_img_box src": "https://contents.kyobobook.co.kr/sih/fit-in/458x0/pdt/3904000339726.jpg",
    "prod_link href": "https://product.kyobobook.co.kr/detail/S000200128281"
  },
  {
    "prod_title": "월간 FLORA 2022년 10월호",
    "portrait_img_box src": "",
    "prod_link href": "https://ebook-product.kyobobook.co.kr/dig/epd/ebook/E000005018101"
  },
  {
    "prod_title": "월간 FLORA 2022년 9월호",
    "portrait_img_box src": "",
    "prod_link href": "https://ebook-product.kyobobook.co.kr/dig/epd/ebook/E000005018095"
  },
  {
    "prod_title": "월간 플로라(Flora)(2022년 8월호)",
    "portrait_img_box src": "https://contents.kyobobook.co.kr/sih/fit-in/458x0/pdt/3904000285214.jpg",
    "prod_link href": "https://product.kyobobook.co.kr/detail/S000000327681"
  },
  {
    "prod_title": "월간 FLORA 2022년 8월호",
    "portrait_img_box src": "",
    "prod_link href": "https://ebook-product.kyobobook.co.kr/dig/epd/ebook/E000003630239"
  },
  {
    "prod_title": "월간 플로라(Flora)(2022년 7월호)",
    "portrait_img_box src": "https://contents.kyobobook.co.kr/sih/fit-in/458x0/pdt/3904000284088.jpg",
    "prod_link href": "https://product.kyobobook.co.kr/detail/S000000327568"
  },
  {
    "prod_title": "월간 FLORA 2022년 7월호",
    "portrait_img_box src": "",
    "prod_link href": "https://ebook-product.kyobobook.co.kr/dig/epd/ebook/E000003625237"
  },
  {
    "prod_title": "월간 플로라(Flora)(2022년 6월호)",
    "portrait_img_box src": "https://contents.kyobobook.co.kr/sih/fit-in/458x0/pdt/3904000283081.jpg",
    "prod_link href": "https://product.kyobobook.co.kr/detail/S000000327468"
  },
  {
    "prod_title": "월간 FLORA 2022년 6월호",
    "portrait_img_box src": "",
    "prod_link href": "https://ebook-product.kyobobook.co.kr/dig/epd/ebook/E000003621220"
  },
  {
    "prod_title": "월간 플로라(Flora)(2022년 5월호)",
    "portrait_img_box src": "https://contents.kyobobook.co.kr/sih/fit-in/458x0/pdt/3904000282046.jpg",
    "prod_link href": "https://product.kyobobook.co.kr/detail/S000000327364"
  },
  {
    "prod_title": "월간 FLORA 2022년 5월호",
    "portrait_img_box src": "",
    "prod_link href": "https://ebook-product.kyobobook.co.kr/dig/epd/ebook/E000003617351"
  },
  {
    "prod_title": "월간 FLORA 2022년 4월호",
    "portrait_img_box src": "",
    "prod_link href": "https://ebook-product.kyobobook.co.kr/dig/epd/ebook/E000003612851"
  },
  {
    "prod_title": "월간 플로라(Flora)(2022년 4월호)",
    "portrait_img_box src": "https://contents.kyobobook.co.kr/sih/fit-in/458x0/pdt/3904000281827.jpg",
    "prod_link href": "https://product.kyobobook.co.kr/detail/S000000327342"
  },
  {
    "prod_title": "월간 플라워뉴스 2022년 3월호",
    "portrait_img_box src": "",
    "prod_link href": "https://ebook-product.kyobobook.co.kr/dig/epd/ebook/E000003609146"
  },
  {
    "prod_title": "월간 플로라(Flora)(2022년 3월호)",
    "portrait_img_box src": "https://contents.kyobobook.co.kr/sih/fit-in/458x0/pdt/3904000292236.jpg",
    "prod_link href": "https://product.kyobobook.co.kr/detail/S000000328383"
  },
  {
    "prod_title": "월간 FLORA 2022년 3월호",
    "portrait_img_box src": "",
    "prod_link href": "https://ebook-product.kyobobook.co.kr/dig/epd/ebook/E000003607540"
  },
  {
    "prod_title": "",
    "portrait_img_box src": "",
    "prod_link href": "https://product.kyobobook.co.kr/detail/S000000328305"
  },
  {
    "prod_title": "월간 FLORA 2022년 2월호",
    "portrait_img_box src": "",
    "prod_link href": "https://ebook-product.kyobobook.co.kr/dig/epd/ebook/E000003604048"
  },
  {
    "prod_title": "월간 플라워뉴스 2022년 2월호",
    "portrait_img_box src": "",
    "prod_link href": "https://ebook-product.kyobobook.co.kr/dig/epd/ebook/E000003604049"
  },
  {
    "prod_title": "Plant space",
    "portrait_img_box src": "",
    "prod_link href": "https://ebook-product.kyobobook.co.kr/dig/epd/ebook/E000003604403"
  },
  {
    "prod_title": "월간 FLORA 2022년 1월호",
    "portrait_img_box src": "",
    "prod_link href": "https://ebook-product.kyobobook.co.kr/dig/epd/ebook/E000003599626"
  },
  {
    "prod_title": "월간 플라워뉴스 2022년 1월호",
    "portrait_img_box src": "",
    "prod_link href": "https://ebook-product.kyobobook.co.kr/dig/epd/ebook/E000003599627"
  },
  {
    "prod_title": "",
    "portrait_img_box src": "",
    "prod_link href": "https://product.kyobobook.co.kr/detail/S000000328188"
  },
  {
    "prod_title": "",
    "portrait_img_box src": "",
    "prod_link href": "https://product.kyobobook.co.kr/detail/S000000328069"
  }
]